yads/__init__.py
yads/_dependencies.py
yads/constraints.py
yads/exceptions.py
yads/py.typed
yads/spec.py
yads/types.py
yads/converters/__init__.py
yads/converters/base.py
yads/converters/polars_converter.py
yads/converters/pyarrow_converter.py
yads/converters/pydantic_converter.py
yads/converters/pyspark_converter.py
yads/converters/sql/__init__.py
yads/converters/sql/ast_converter.py
yads/converters/sql/sql_converter.py
yads/converters/sql/validators/__init__.py
yads/converters/sql/validators/ast_validation_rules.py
yads/converters/sql/validators/ast_validator.py
yads/loaders/__init__.py
yads/loaders/base.py
yads/loaders/polars_loader.py
yads/loaders/pyarrow_loader.py
yads/loaders/pyspark_loader.py
yads/loaders/yaml_loader.py
yads/registries/__init__.py
yads/registries/base.py
yads/registries/filesystem_registry.py
yads/serializers/__init__.py
yads/serializers/constraint_serializer.py
yads/serializers/spec_serializer.py
yads/serializers/type_serializer.py
yads-0.0.3.dist-info/METADATA
yads-0.0.3.dist-info/WHEEL
yads-0.0.3.dist-info/licenses/LICENSE
yads-0.0.3.dist-info/RECORD
