Metadata-Version: 2.4
Name: yads
Version: 0.0.3
Summary: A lightweight library for managing and validating data schemas from YAML specifications
Author-email: Erich Silva <erich.hs13@gmail.com>
License-File: LICENSE
Requires-Python: >=3.10
Requires-Dist: pyyaml>=5.4.0
